setup.py
LoggedExample/__init__.py
LoggedExample/__main__.py
LoggedExample/cli.py
loggedexample-1.2.5.dist-info/METADATA
loggedexample-1.2.5.dist-info/WHEEL
loggedexample-1.2.5.dist-info/entry_points.txt
loggedexample-1.2.5.dist-info/top_level.txt
loggedexample-1.2.5.dist-info/RECORD
