Metadata-Version: 2.4
Name: LoggedExample
Version: 1.2.5
Summary: A logging example application with sudo detection and log rotation
Author-email: Wilgat Wong <wilgat.wong@gmail.com>
License: MIT
Project-URL: Homepage, https://github.com/Wilgat/LoggedExample
Project-URL: Repository, https://github.com/Wilgat/LoggedExample
Project-URL: Issues, https://github.com/Wilgat/LoggedExample/issues
Keywords: logging,sudo,chronicle,example
Requires-Python: !=3.0.*,!=3.1.*,!=3.2.*,!=3.3.*,!=3.4.*,>=2.7
Requires-Dist: ChronicleLogger>=1.2.3
